README
setup.py
test/test_gamut.py
test/test_simple.py
test/test_unicode.py
tiddlywebplugins/__init__.py
tiddlywebplugins/redisstore.py
tiddlywebplugins.redisstore.egg-info/PKG-INFO
tiddlywebplugins.redisstore.egg-info/SOURCES.txt
tiddlywebplugins.redisstore.egg-info/dependency_links.txt
tiddlywebplugins.redisstore.egg-info/namespace_packages.txt
tiddlywebplugins.redisstore.egg-info/not-zip-safe
tiddlywebplugins.redisstore.egg-info/requires.txt
tiddlywebplugins.redisstore.egg-info/top_level.txt