Metadata-Version: 1.0
Name: tiddlywebplugins.redisstore
Version: 0.2
Summary: TiddlyWeb store using Redis
Home-page: http://pypi.python.org/pypi/tiddlywebplugins.redisstore
Author: Chris Dent
Author-email: cdent@peermore.com
License: UNKNOWN
Platform: Posix; MacOS X; Windows
